duffie2013/__init__.py
duffie2013/clear_sky.py
duffie2013/diffuse.py
duffie2013/extraterrestrial.py
duffie2013/sun.py
duffie2013/version.py
duffie2013-0.2.0.dist-info/AUTHORS.rst
duffie2013-0.2.0.dist-info/LICENSE
duffie2013-0.2.0.dist-info/METADATA
duffie2013-0.2.0.dist-info/WHEEL
duffie2013-0.2.0.dist-info/top_level.txt
duffie2013-0.2.0.dist-info/RECORD
